{
    "camera_stage_mapping_calibration": {
        "backlash": 0.0,
        "backlash_vector": [
            0.0,
            0.0,
            0.0
        ],
        "image_to_stage_displacement": [
            [
                -0.0012067713954007876,
                -1.0026877733034139
            ],
            [
                -1.0026877733034147,
                -0.0012067713953998979
            ]
        ]
    },
    "linear_calibration_X": {
        "backlash": 0,
        "backlash_corrected_moves": [
            [
                [
                    256.0,
                    -358.40000000000003,
                    0.0
                ]
            ],
            [
                [
                    358.0,
                    -256.0
                ]
            ],
            [
                1715786815.4806368
            ]
        ],
        "exponential_moves": [
            [
                [
                    0.0,
                    0.0,
                    0.0
                ],
                [
                    1.0,
                    0.0,
                    0.0
                ],
                [
                    2.0,
                    0.0,
                    0.0
                ],
                [
                    4.0,
                    0.0,
                    0.0
                ],
                [
                    8.0,
                    0.0,
                    0.0
                ],
                [
                    16.0,
                    0.0,
                    0.0
                ],
                [
                    32.0,
                    0.0,
                    0.0
                ],
                [
                    64.0,
                    0.0,
                    0.0
                ],
                [
                    128.0,
                    0.0,
                    0.0
                ],
                [
                    0.0,
                    128.0,
                    0.0
                ],
                [
                    64.0,
                    128.0,
                    0.0
                ],
                [
                    128.0,
                    128.0,
                    0.0
                ],
                [
                    192.0,
                    128.0,
                    0.0
                ],
                [
                    256.0,
                    128.0,
                    0.0
                ],
                [
                    320.0,
                    128.0,
                    0.0
                ],
                [
                    384.0,
                    128.0,
                    0.0
                ]
            ],
            [
                [
                    0.0,
                    0.0
                ],
                [
                    0.0,
                    -1.0
                ],
                [
                    0.0,
                    -2.0
                ],
                [
                    0.0,
                    -4.0
                ],
                [
                    0.0,
                    -8.0
                ],
                [
                    0.0,
                    -16.0
                ],
                [
                    0.0,
                    -32.0
                ],
                [
                    0.0,
                    -64.0
                ],
                [
                    0.0,
                    -128.0
                ],
                [
                    -128.0,
                    0.0
                ],
                [
                    -128.0,
                    -64.0
                ],
                [
                    -128.0,
                    -128.0
                ],
                [
                    -128.0,
                    -192.0
                ],
                [
                    -128.0,
                    -256.0
                ],
                [
                    -128.0,
                    -320.0
                ],
                [
                    -128.0,
                    -384.0
                ]
            ],
            [
                1715786803.847728,
                1715786804.2093902,
                1715786804.615663,
                1715786804.985069,
                1715786805.360099,
                1715786805.740843,
                1715786806.114272,
                1715786806.485475,
                1715786806.858428,
                1715786807.235971,
                1715786807.6139898,
                1715786807.987776,
                1715786808.5471182,
                1715786808.9387898,
                1715786809.3384771,
                1715786809.719718
            ]
        ],
        "fractional_error": 0.00043749718015130676,
        "image_direction": [
            0.6390412089483677,
            -0.7691724990311397
        ],
        "linear_moves": [
            [
                [
                    0.0,
                    0.0,
                    0.0
                ],
                [
                    -51.2,
                    0.0,
                    0.0
                ],
                [
                    -102.4,
                    0.0,
                    0.0
                ],
                [
                    -153.60000000000002,
                    0.0,
                    0.0
                ],
                [
                    -204.8,
                    0.0,
                    0.0
                ],
                [
                    -256.0,
                    0.0,
                    0.0
                ],
                [
                    -307.20000000000005,
                    0.0,
                    0.0
                ],
                [
                    -358.40000000000003,
                    0.0,
                    0.0
                ],
                [
                    -358.40000000000003,
                    0.0,
                    0.0
                ],
                [
                    51.2,
                    -358.40000000000003,
                    0.0
                ],
                [
                    102.4,
                    -358.40000000000003,
                    0.0
                ],
                [
                    153.60000000000002,
                    -358.40000000000003,
                    0.0
                ],
                [
                    204.8,
                    -358.40000000000003,
                    0.0
                ],
                [
                    256.0,
                    -358.40000000000003,
                    0.0
                ]
            ],
            [
                [
                    0.0,
                    0.0
                ],
                [
                    0.0,
                    51.0
                ],
                [
                    0.0,
                    101.99999999999999
                ],
                [
                    0.0,
                    153.0
                ],
                [
                    0.0,
                    204.0
                ],
                [
                    0.0,
                    256.0
                ],
                [
                    0.0,
                    307.0
                ],
                [
                    0.0,
                    358.0
                ],
                [
                    0.0,
                    358.0
                ],
                [
                    358.0,
                    -51.0
                ],
                [
                    358.0,
                    -102.0
                ],
                [
                    358.0,
                    -153.0
                ],
                [
                    358.0,
                    -204.00000000000003
                ],
                [
                    358.0,
                    -256.0
                ]
            ],
            [
                1715786810.0870998,
                1715786810.453878,
                1715786810.8429499,
                1715786811.214027,
                1715786811.614192,
                1715786812.009585,
                1715786812.380136,
                1715786812.7627242,
                1715786813.131853,
                1715786813.52299,
                1715786813.906236,
                1715786814.287123,
                1715786814.670621,
                1715786815.057423
            ]
        ],
        "move_history": [
            [
                1715786803.848089,
                1715786803.8481688,
                1715786804.210088,
                1715786804.2101388,
                1715786804.616332,
                1715786804.616384,
                1715786804.985754,
                1715786804.985806,
                1715786805.360815,
                1715786805.360867,
                1715786805.7415192,
                1715786805.7415721,
                1715786806.1149461,
                1715786806.115,
                1715786806.486134,
                1715786806.486187,
                1715786806.859343,
                1715786806.8593972,
                1715786807.2366478,
                1715786807.236701,
                1715786807.615361,
                1715786807.615426,
                1715786807.988432,
                1715786807.988485,
                1715786808.547842,
                1715786808.547897,
                1715786808.93949,
                1715786808.939544,
                1715786809.3392022,
                1715786809.339255,
                1715786809.720458,
                1715786809.720514,
                1715786810.08713,
                1715786810.087223,
                1715786810.454365,
                1715786810.454417,
                1715786810.843467,
                1715786810.843523,
                1715786811.2145221,
                1715786811.2145762,
                1715786811.614671,
                1715786811.614725,
                1715786812.010166,
                1715786812.010224,
                1715786812.380744,
                1715786812.3807979,
                1715786813.131907,
                1715786813.131993,
                1715786813.523505,
                1715786813.5235572,
                1715786813.906718,
                1715786813.906772,
                1715786814.287601,
                1715786814.287658,
                1715786814.671102,
                1715786814.671155,
                1715786815.4806778,
                1715786815.4808042,
                1715786815.480809,
                1715786815.4808378
            ],
            [
                [
                    0.0,
                    0.0,
                    0.0
                ],
                [
                    0.0,
                    1.0,
                    0.0
                ],
                [
                    0.0,
                    1.0,
                    0.0
                ],
                [
                    0.0,
                    2.0,
                    0.0
                ],
                [
                    0.0,
                    2.0,
                    0.0
                ],
                [
                    0.0,
                    4.0,
                    0.0
                ],
                [
                    0.0,
                    4.0,
                    0.0
                ],
                [
                    0.0,
                    8.0,
                    0.0
                ],
                [
                    0.0,
                    8.0,
                    0.0
                ],
                [
                    0.0,
                    16.0,
                    0.0
                ],
                [
                    0.0,
                    16.0,
                    0.0
                ],
                [
                    0.0,
                    32.0,
                    0.0
                ],
                [
                    0.0,
                    32.0,
                    0.0
                ],
                [
                    0.0,
                    64.0,
                    0.0
                ],
                [
                    0.0,
                    64.0,
                    0.0
                ],
                [
                    0.0,
                    128.0,
                    0.0
                ],
                [
                    0.0,
                    128.0,
                    0.0
                ],
                [
                    128.0,
                    0.0,
                    0.0
                ],
                [
                    128.0,
                    0.0,
                    0.0
                ],
                [
                    128.0,
                    64.0,
                    0.0
                ],
                [
                    128.0,
                    64.0,
                    0.0
                ],
                [
                    128.0,
                    128.0,
                    0.0
                ],
                [
                    128.0,
                    128.0,
                    0.0
                ],
                [
                    128.0,
                    192.0,
                    0.0
                ],
                [
                    128.0,
                    192.0,
                    0.0
                ],
                [
                    128.0,
                    256.0,
                    0.0
                ],
                [
                    128.0,
                    256.0,
                    0.0
                ],
                [
                    128.0,
                    320.0,
                    0.0
                ],
                [
                    128.0,
                    320.0,
                    0.0
                ],
                [
                    128.0,
                    384.0,
                    0.0
                ],
                [
                    128.0,
                    384.0,
                    0.0
                ],
                [
                    0.0,
                    0.0,
                    0.0
                ],
                [
                    0.0,
                    0.0,
                    0.0
                ],
                [
                    0.0,
                    -51.2,
                    0.0
                ],
                [
                    0.0,
                    -51.2,
                    0.0
                ],
                [
                    0.0,
                    -102.4,
                    0.0
                ],
                [
                    0.0,
                    -102.4,
                    0.0
                ],
                [
                    0.0,
                    -153.60000000000002,
                    0.0
                ],
                [
                    0.0,
                    -153.60000000000002,
                    0.0
                ],
                [
                    0.0,
                    -204.8,
                    0.0
                ],
                [
                    0.0,
                    -204.8,
                    0.0
                ],
                [
                    0.0,
                    -256.0,
                    0.0
                ],
                [
                    0.0,
                    -256.0,
                    0.0
                ],
                [
                    0.0,
                    -307.20000000000005,
                    0.0
                ],
                [
                    0.0,
                    -307.20000000000005,
                    0.0
                ],
                [
                    0.0,
                    -358.40000000000003,
                    0.0
                ],
                [
                    0.0,
                    -358.40000000000003,
                    0.0
                ],
                [
                    -358.40000000000003,
                    51.2,
                    0.0
                ],
                [
                    -358.40000000000003,
                    51.2,
                    0.0
                ],
                [
                    -358.40000000000003,
                    102.4,
                    0.0
                ],
                [
                    -358.40000000000003,
                    102.4,
                    0.0
                ],
                [
                    -358.40000000000003,
                    153.60000000000002,
                    0.0
                ],
                [
                    -358.40000000000003,
                    153.60000000000002,
                    0.0
                ],
                [
                    -358.40000000000003,
                    204.8,
                    0.0
                ],
                [
                    -358.40000000000003,
                    204.8,
                    0.0
                ],
                [
                    -358.40000000000003,
                    256.0,
                    0.0
                ],
                [
                    -358.40000000000003,
                    256.0,
                    0.0
                ],
                [
                    0.0,
                    0.0,
                    0.0
                ],
                [
                    0.0,
                    0.0,
                    0.0
                ],
                [
                    0.0,
                    0.0,
                    0.0
                ]
            ]
        ],
        "pixels_per_step": 0.9985007890335181,
        "pixels_per_step_vector": [
            0.6380831513598785,
            -0.7680193471854759
        ],
        "stage_axis": "X",
        "stage_direction": [
            0.7693135885883988,
            -0.6388713504401646,
            0.0
        ]
    },
    "linear_calibration_Y": {
        "backlash": 0,
        "backlash_corrected_moves": [
            [
                [
                    -358.40000000000003,
                    256.0,
                    0.0
                ]
            ],
            [
                [
                    -256.0,
                    358.0
                ]
            ],
            [
                1715786803.236435
            ]
        ],
        "exponential_moves": [
            [
                [
                    0.0,
                    0.0,
                    0.0
                ],
                [
                    0.0,
                    1.0,
                    0.0
                ],
                [
                    0.0,
                    2.0,
                    0.0
                ],
                [
                    0.0,
                    4.0,
                    0.0
                ],
                [
                    0.0,
                    8.0,
                    0.0
                ],
                [
                    0.0,
                    16.0,
                    0.0
                ],
                [
                    0.0,
                    32.0,
                    0.0
                ],
                [
                    0.0,
                    64.0,
                    0.0
                ],
                [
                    0.0,
                    128.0,
                    0.0
                ],
                [
                    128.0,
                    0.0,
                    0.0
                ],
                [
                    128.0,
                    64.0,
                    0.0
                ],
                [
                    128.0,
                    128.0,
                    0.0
                ],
                [
                    128.0,
                    192.0,
                    0.0
                ],
                [
                    128.0,
                    256.0,
                    0.0
                ],
                [
                    128.0,
                    320.0,
                    0.0
                ],
                [
                    128.0,
                    384.0,
                    0.0
                ]
            ],
            [
                [
                    0.0,
                    0.0
                ],
                [
                    -1.0,
                    0.0
                ],
                [
                    -2.0,
                    0.0
                ],
                [
                    -4.0,
                    0.0
                ],
                [
                    -8.0,
                    0.0
                ],
                [
                    -16.0,
                    0.0
                ],
                [
                    -32.0,
                    0.0
                ],
                [
                    -64.0,
                    0.0
                ],
                [
                    -128.0,
                    0.0
                ],
                [
                    0.0,
                    -128.0
                ],
                [
                    -64.0,
                    -128.0
                ],
                [
                    -128.0,
                    -128.0
                ],
                [
                    -192.0,
                    -128.0
                ],
                [
                    -256.0,
                    -128.0
                ],
                [
                    -320.0,
                    -128.0
                ],
                [
                    -384.0,
                    -128.0
                ]
            ],
            [
                1715786791.8633149,
                1715786792.253488,
                1715786792.605514,
                1715786792.97776,
                1715786793.374764,
                1715786793.74578,
                1715786794.131865,
                1715786794.491564,
                1715786794.8614998,
                1715786795.273132,
                1715786795.661154,
                1715786796.0387928,
                1715786796.434114,
                1715786796.821955,
                1715786797.2025259,
                1715786797.596457
            ]
        ],
        "fractional_error": 0.0004374971801513051,
        "image_direction": [
            0.7691724990311397,
            -0.6390412089483677
        ],
        "linear_moves": [
            [
                [
                    0.0,
                    0.0,
                    0.0
                ],
                [
                    0.0,
                    -51.2,
                    0.0
                ],
                [
                    0.0,
                    -102.4,
                    0.0
                ],
                [
                    0.0,
                    -153.60000000000002,
                    0.0
                ],
                [
                    0.0,
                    -204.8,
                    0.0
                ],
                [
                    0.0,
                    -256.0,
                    0.0
                ],
                [
                    0.0,
                    -307.20000000000005,
                    0.0
                ],
                [
                    0.0,
                    -358.40000000000003,
                    0.0
                ],
                [
                    0.0,
                    -358.40000000000003,
                    0.0
                ],
                [
                    -358.40000000000003,
                    51.2,
                    0.0
                ],
                [
                    -358.40000000000003,
                    102.4,
                    0.0
                ],
                [
                    -358.40000000000003,
                    153.60000000000002,
                    0.0
                ],
                [
                    -358.40000000000003,
                    204.8,
                    0.0
                ],
                [
                    -358.40000000000003,
                    256.0,
                    0.0
                ]
            ],
            [
                [
                    0.0,
                    0.0
                ],
                [
                    51.0,
                    0.0
                ],
                [
                    102.0,
                    0.0
                ],
                [
                    153.0,
                    0.0
                ],
                [
                    204.0,
                    0.0
                ],
                [
                    256.0,
                    0.0
                ],
                [
                    307.0,
                    0.0
                ],
                [
                    358.0,
                    0.0
                ],
                [
                    358.0,
                    0.0
                ],
                [
                    -51.0,
                    358.0
                ],
                [
                    -102.0,
                    357.99999999999994
                ],
                [
                    -153.0,
                    358.0
                ],
                [
                    -204.0,
                    358.0
                ],
                [
                    -256.0,
                    358.0
                ]
            ],
            [
                1715786797.966945,
                1715786798.340184,
                1715786798.715303,
                1715786799.0754938,
                1715786799.450887,
                1715786799.808843,
                1715786800.188222,
                1715786800.57197,
                1715786800.937174,
                1715786801.3110242,
                1715786801.7080781,
                1715786802.0899541,
                1715786802.473176,
                1715786802.8555908
            ]
        ],
        "move_history": [
            [
                1715786791.863717,
                1715786791.863772,
                1715786792.254265,
                1715786792.254326,
                1715786792.606186,
                1715786792.60624,
                1715786792.978442,
                1715786792.978494,
                1715786793.3754601,
                1715786793.375513,
                1715786793.746516,
                1715786793.746575,
                1715786794.132891,
                1715786794.1330292,
                1715786794.492222,
                1715786794.4922721,
                1715786794.8624582,
                1715786794.862512,
                1715786795.273946,
                1715786795.274303,
                1715786795.661843,
                1715786795.6618948,
                1715786796.0394921,
                1715786796.039547,
                1715786796.434807,
                1715786796.434861,
                1715786796.82261,
                1715786796.8226602,
                1715786797.203213,
                1715786797.2032661,
                1715786797.597142,
                1715786797.597195,
                1715786797.966971,
                1715786797.967059,
                1715786798.340694,
                1715786798.340749,
                1715786798.715778,
                1715786798.71583,
                1715786799.0759811,
                1715786799.0760362,
                1715786799.4513521,
                1715786799.451406,
                1715786799.809421,
                1715786799.8094752,
                1715786800.188811,
                1715786800.188875,
                1715786800.9371982,
                1715786800.937288,
                1715786801.3115132,
                1715786801.3115678,
                1715786801.708562,
                1715786801.7086148,
                1715786802.090445,
                1715786802.090498,
                1715786802.473655,
                1715786802.473707,
                1715786803.236476,
                1715786803.2365701,
                1715786803.236573,
                1715786803.236605
            ],
            [
                [
                    0.0,
                    0.0,
                    0.0
                ],
                [
                    1.0,
                    0.0,
                    0.0
                ],
                [
                    1.0,
                    0.0,
                    0.0
                ],
                [
                    2.0,
                    0.0,
                    0.0
                ],
                [
                    2.0,
                    0.0,
                    0.0
                ],
                [
                    4.0,
                    0.0,
                    0.0
                ],
                [
                    4.0,
                    0.0,
                    0.0
                ],
                [
                    8.0,
                    0.0,
                    0.0
                ],
                [
                    8.0,
                    0.0,
                    0.0
                ],
                [
                    16.0,
                    0.0,
                    0.0
                ],
                [
                    16.0,
                    0.0,
                    0.0
                ],
                [
                    32.0,
                    0.0,
                    0.0
                ],
                [
                    32.0,
                    0.0,
                    0.0
                ],
                [
                    64.0,
                    0.0,
                    0.0
                ],
                [
                    64.0,
                    0.0,
                    0.0
                ],
                [
                    128.0,
                    0.0,
                    0.0
                ],
                [
                    128.0,
                    0.0,
                    0.0
                ],
                [
                    0.0,
                    128.0,
                    0.0
                ],
                [
                    0.0,
                    128.0,
                    0.0
                ],
                [
                    64.0,
                    128.0,
                    0.0
                ],
                [
                    64.0,
                    128.0,
                    0.0
                ],
                [
                    128.0,
                    128.0,
                    0.0
                ],
                [
                    128.0,
                    128.0,
                    0.0
                ],
                [
                    192.0,
                    128.0,
                    0.0
                ],
                [
                    192.0,
                    128.0,
                    0.0
                ],
                [
                    256.0,
                    128.0,
                    0.0
                ],
                [
                    256.0,
                    128.0,
                    0.0
                ],
                [
                    320.0,
                    128.0,
                    0.0
                ],
                [
                    320.0,
                    128.0,
                    0.0
                ],
                [
                    384.0,
                    128.0,
                    0.0
                ],
                [
                    384.0,
                    128.0,
                    0.0
                ],
                [
                    0.0,
                    0.0,
                    0.0
                ],
                [
                    0.0,
                    0.0,
                    0.0
                ],
                [
                    -51.2,
                    0.0,
                    0.0
                ],
                [
                    -51.2,
                    0.0,
                    0.0
                ],
                [
                    -102.4,
                    0.0,
                    0.0
                ],
                [
                    -102.4,
                    0.0,
                    0.0
                ],
                [
                    -153.60000000000002,
                    0.0,
                    0.0
                ],
                [
                    -153.60000000000002,
                    0.0,
                    0.0
                ],
                [
                    -204.8,
                    0.0,
                    0.0
                ],
                [
                    -204.8,
                    0.0,
                    0.0
                ],
                [
                    -256.0,
                    0.0,
                    0.0
                ],
                [
                    -256.0,
                    0.0,
                    0.0
                ],
                [
                    -307.20000000000005,
                    0.0,
                    0.0
                ],
                [
                    -307.20000000000005,
                    0.0,
                    0.0
                ],
                [
                    -358.40000000000003,
                    0.0,
                    0.0
                ],
                [
                    -358.40000000000003,
                    0.0,
                    0.0
                ],
                [
                    51.2,
                    -358.40000000000003,
                    0.0
                ],
                [
                    51.2,
                    -358.40000000000003,
                    0.0
                ],
                [
                    102.4,
                    -358.40000000000003,
                    0.0
                ],
                [
                    102.4,
                    -358.40000000000003,
                    0.0
                ],
                [
                    153.60000000000002,
                    -358.40000000000003,
                    0.0
                ],
                [
                    153.60000000000002,
                    -358.40000000000003,
                    0.0
                ],
                [
                    204.8,
                    -358.40000000000003,
                    0.0
                ],
                [
                    204.8,
                    -358.40000000000003,
                    0.0
                ],
                [
                    256.0,
                    -358.40000000000003,
                    0.0
                ],
                [
                    256.0,
                    -358.40000000000003,
                    0.0
                ],
                [
                    0.0,
                    0.0,
                    0.0
                ],
                [
                    0.0,
                    0.0,
                    0.0
                ],
                [
                    0.0,
                    0.0,
                    0.0
                ]
            ]
        ],
        "pixels_per_step": 0.9985007890335181,
        "pixels_per_step_vector": [
            0.7680193471854759,
            -0.6380831513598785
        ],
        "stage_axis": "Y",
        "stage_direction": [
            0.6388713504401646,
            -0.7693135885883988,
            0.0
        ]
    }
}